src/__init__.py
src/astro.py
astro_mcp-0.1.0.dist-info/METADATA
astro_mcp-0.1.0.dist-info/WHEEL
astro_mcp-0.1.0.dist-info/entry_points.txt
astro_mcp-0.1.0.dist-info/RECORD
