Metadata-Version: 2.4
Name: astro-mcp
Version: 0.1.0
Summary: Model Context Protocol (MCP) server for interacting with the Astro and Airflow APIs
Requires-Python: >=3.12
Requires-Dist: aiohttp>=3.9.0
Requires-Dist: mcp[cli]>=1.0.0
Requires-Dist: pyyaml>=6.0.1
